persianBrokers/__init__.py
persianBrokers/exception.py
persianBrokers/utils.py
persianBrokers/mobinSarmaye/__init__.py
persianBrokers/mobinSarmaye/mobinSarmaye.py
persianBrokers-0.1.3.dist-info/METADATA
persianBrokers-0.1.3.dist-info/WHEEL
persianBrokers-0.1.3.dist-info/top_level.txt
persianBrokers-0.1.3.dist-info/RECORD
