Metadata-Version: 2.1
Name: persianBrokers
Version: 0.1.3
Summary: description
Home-page: UNKNOWN
Author: M.Mortaz,M.Moalaghi
Author-email: hdhshd@dd.com
License: UNKNOWN
Platform: UNKNOWN
Requires-Dist: requests
